krrood/__init__.py
krrood/singleton.py
krrood/utils.py
krrood/adapters/__init__.py
krrood/adapters/json_serializer.py
krrood/class_diagrams/__init__.py
krrood/class_diagrams/attribute_introspector.py
krrood/class_diagrams/class_diagram.py
krrood/class_diagrams/failures.py
krrood/class_diagrams/utils.py
krrood/class_diagrams/wrapped_field.py
krrood/entity_query_language/__init__.py
krrood/entity_query_language/cache_data.py
krrood/entity_query_language/conclusion.py
krrood/entity_query_language/conclusion_selector.py
krrood/entity_query_language/entity.py
krrood/entity_query_language/enums.py
krrood/entity_query_language/failures.py
krrood/entity_query_language/hashed_data.py
krrood/entity_query_language/predicate.py
krrood/entity_query_language/result_quantification_constraint.py
krrood/entity_query_language/rule.py
krrood/entity_query_language/rxnode.py
krrood/entity_query_language/symbol_graph.py
krrood/entity_query_language/symbolic.py
krrood/entity_query_language/utils.py
krrood/entity_query_language/orm/__init__.py
krrood/entity_query_language/orm/model.py
krrood/ontomatic/__init__.py
krrood/ontomatic/failures.py
krrood/ontomatic/property_descriptor/__init__.py
krrood/ontomatic/property_descriptor/attribute_introspector.py
krrood/ontomatic/property_descriptor/mixins.py
krrood/ontomatic/property_descriptor/monitored_container.py
krrood/ontomatic/property_descriptor/property_descriptor.py
krrood/ontomatic/property_descriptor/property_descriptor_relation.py
krrood/ormatic/__init__.py
krrood/ormatic/custom_types.py
krrood/ormatic/dao.py
krrood/ormatic/eql_interface.py
krrood/ormatic/ormatic.py
krrood/ormatic/sqlalchemy_generator.py
krrood/ormatic/utils.py
krrood/ormatic/wrapped_table.py
krrood/ormatic/templates/sqlalchemy_model.py.jinja
krrood-2.0.0.dist-info/METADATA
krrood-2.0.0.dist-info/WHEEL
krrood-2.0.0.dist-info/top_level.txt
krrood-2.0.0.dist-info/RECORD
