Metadata-Version: 2.4
Name: krrood
Version: 2.0.0
Summary: A university data generator based on the LUBM (Lehigh University Benchmark) ontology
Author-email: Abdelrhman Bassiouny <abassiou@uni-bremen.de>, Tom Schierenbeck <tom_sch@uni-bremen.de>
License: MIT
Project-URL: Homepage, https://code-iai.github.io/krrood/intro.html
Project-URL: Repository, https://github.com/code-iai/krrood
Project-URL: Issues, https://github.com/code-iai/krrood/issues
Keywords: lubm,ontology,data-generator,university,benchmark
Classifier: Development Status :: 3 - Alpha
Classifier: Intended Audience :: Developers
Classifier: Intended Audience :: Science/Research
Classifier: License :: OSI Approved :: MIT License
Classifier: Operating System :: OS Independent
Classifier: Programming Language :: Python :: 3
Classifier: Programming Language :: Python :: 3.8
Classifier: Programming Language :: Python :: 3.9
Classifier: Programming Language :: Python :: 3.10
Classifier: Programming Language :: Python :: 3.11
Classifier: Programming Language :: Python :: 3.12
Classifier: Topic :: Software Development :: Libraries :: Python Modules
Classifier: Topic :: Scientific/Engineering
Requires-Python: >=3.10
Provides-Extra: dev
Requires-Dist: pytest>=7.0.0; extra == "dev"
